MoBI_View/__init__.py
MoBI_View/main.py
MoBI_View/core/__init__.py
MoBI_View/core/config.py
MoBI_View/core/data_inlet.py
MoBI_View/core/exceptions.py
MoBI_View/presenters/__init__.py
MoBI_View/presenters/main_app_presenter.py
MoBI_View/views/__init__.py
MoBI_View/views/eeg_plot_widget.py
MoBI_View/views/interfaces.py
MoBI_View/views/main_app_view.py
MoBI_View/views/numeric_plot_widget.py
mobi_view-0.2.1.dist-info/METADATA
mobi_view-0.2.1.dist-info/WHEEL
mobi_view-0.2.1.dist-info/entry_points.txt
mobi_view-0.2.1.dist-info/licenses/LICENSE
mobi_view-0.2.1.dist-info/RECORD
