Metadata-Version: 2.4
Name: mobi-view
Version: 0.2.1
Summary: A real-time biosignal visualization tool for Lab Streaming Layer (LSL) streams.
Author-email: Iktae Kim <iktae.kim@childmind.org>, Adam Santorelli <adam.santorelli@childmind.org>
License-Expression: LGPL-2.1
License-File: LICENSE
Requires-Python: <3.13,>=3.10
Requires-Dist: numpy<2.1.0,>=1.26.4
Requires-Dist: pylsl>=1.17.6
Requires-Dist: pyqt6>=6.9.0
Requires-Dist: pyqtgraph>=0.13.7
